akita/__init__.py
akita/__main__.py
akita/__version__.py
akita/akita.py
akita/display.py
akita/metrics.py
akita/parser.py
akita-0.1.4.dist-info/LICENSE
akita-0.1.4.dist-info/METADATA
akita-0.1.4.dist-info/WHEEL
akita-0.1.4.dist-info/entry_points.txt
akita-0.1.4.dist-info/top_level.txt
akita-0.1.4.dist-info/RECORD
