Metadata-Version: 2.1
Name: akita
Version: 0.1.4
Summary: An HTTP log monitoring tool for your terminal
Home-page: https://github.com/michael-lazar/Akita
Author: Michael Lazar
Author-email: lazar.michael22@gmail.com
License: MIT
Keywords: http log apache nginx monitoring terminal console metrics
Platform: UNKNOWN
Classifier: Intended Audience :: End Users/Desktop
Classifier: Environment :: Console :: Curses
Classifier: Operating System :: MacOS :: MacOS X
Classifier: Operating System :: POSIX
Classifier: Natural Language :: English
Classifier: Programming Language :: Python :: 3.4
Classifier: Programming Language :: Python :: 3.5
Classifier: Programming Language :: Python :: 3.6
Classifier: Programming Language :: Python :: 3.7
Classifier: Programming Language :: Python :: 3.8
Classifier: Topic :: Terminals
Classifier: Topic :: Internet :: WWW/HTTP :: HTTP Servers
Requires-Python: >=3.4
Provides-Extra: test
Requires-Dist: pytest ; extra == 'test'
